<annotation>
	<folder>train</folder>
	<filename>IMG_20180426_142245829.jpg</filename>
	<path>C:/MyTensor1/models/research/object_detection/images/train/IMG_20180426_142245829.jpg</path>
	<source>
		<database>Unknown</database>
	</source>
	<size>
		<width>338</width>
		<height>600</height>
		<depth>3</depth>
	</size>
	<segmented>0</segmented>
	<object>
		<name>goodday</name>
		<pose>Unspecified</pose>
		<truncated>0</truncated>
		<difficult>0</difficult>
		<bndbox>
			<xmin>61</xmin>
			<ymin>104</ymin>
			<xmax>136</xmax>
			<ymax>252</ymax>
		</bndbox>
	</object>
	<object>
		<name>kurkure</name>
		<pose>Unspecified</pose>
		<truncated>0</truncated>
		<difficult>0</difficult>
		<bndbox>
			<xmin>88</xmin>
			<ymin>216</ymin>
			<xmax>258</xmax>
			<ymax>377</ymax>
		</bndbox>
	</object>
	<object>
		<name>colddrink</name>
		<pose>Unspecified</pose>
		<truncated>0</truncated>
		<difficult>0</difficult>
		<bndbox>
			<xmin>184</xmin>
			<ymin>160</ymin>
			<xmax>317</xmax>
			<ymax>258</ymax>
		</bndbox>
	</object>
	<object>
		<name>biscuit</name>
		<pose>Unspecified</pose>
		<truncated>0</truncated>
		<difficult>0</difficult>
		<bndbox>
			<xmin>139</xmin>
			<ymin>156</ymin>
			<xmax>229</xmax>
			<ymax>266</ymax>
		</bndbox>
	</object>
</annotation>
